jangli/case_type.py
jangli/json_to_object.py
jangli/list_of_object.py
jangli/retry.py
jangli-1.2.1.dist-info/LICENSE
jangli-1.2.1.dist-info/METADATA
jangli-1.2.1.dist-info/WHEEL
jangli-1.2.1.dist-info/top_level.txt
jangli-1.2.1.dist-info/RECORD
