Metadata-Version: 2.1
Name: jangli
Version: 1.2.1
Summary: Data Object Mapping
Home-page: https://github.com/AbhimanyuHK/Jangli
Author: Abimanyu H K
Author-email: manyu1994@hotmail.com
License: MIT License : Copyright (c) 2019 Abhimanyu Haralukallu
Platform: UNKNOWN
